[
    {
        "address": "draco.109@gmail.com",
        "watchlist": [
            {
                "product": "rtx-2060-super",
                "price": 150000
            },
            {
                "product": "rtx-2070-super",
                "price": 177000
            },
            {
                "product": "rtx-3060-ti",
                "price": 200000
            },
            {
                "product": "rtx-3070",
                "price": 226500
            },
            {
                "product": "rtx-3080",
                "price": 250000
            },
            {
                "product": "rtx-3090",
                "price": 250000
            },
            {
                "product": "rx-5700",
                "price": 135000
            },
            {
                "product": "rx-5700-xt",
                "price": 162000
            }
        ]
    },
    {
        "address": "beresviktor07@gmail.com",
        "watchlist": [
            {
                "product": "rtx-2060",
                "price": 140000
            },{
                "product": "rx-5600-xt",
                "price": 140000
            },{
                "product": "rtx-2070",
                "price": 160000
            },{
                "product": "rtx-3050",
                "price": 160000
            },{
                "product": "rtx-3060",
                "price": 160000
            }
        ]
    }
]
